{
  "buildCommand" : {
    "command" : "build",
    "skipDependencies" : false,
    "style" : "buildOnly"
  },
  "configuredTargets" : [
    {
      "guid" : "18c1723432283e0cc55f10a6dcfd9e0288a783a885d8b0b3beb2e9f90bde3f49"
    }
  ],
  "containerPath" : "/Users/a1111/Downloads/Telegram Desktop/fitbod-master/ios/Runner.xcworkspace",
  "continueBuildingAfterErrors" : false,
  "dependencyScope" : "workspace",
  "enableIndexBuildArena" : false,
  "hideShellScriptEnvironment" : false,
  "parameters" : {
    "action" : "build",
    "activeArchitecture" : "x86_64",
    "activeRunDestination" : {
      "disableOnlyActiveArch" : false,
      "platform" : "iphonesimulator",
      "sdk" : "iphonesimulator18.2",
      "sdkVariant" : "iphonesimulator",
      "supportedArchitectures" : [
        "x86_64"
      ],
      "targetArchitecture" : "x86_64"
    },
    "arenaInfo" : {
      "buildIntermediatesPath" : "/Users/a1111/Downloads/Telegram Desktop/fitbod-master/ios/DerivedData3/Runner/Build/Intermediates.noindex",
      "buildProductsPath" : "/Users/a1111/Downloads/Telegram Desktop/fitbod-master/ios/DerivedData3/Runner/Build/Products",
      "derivedDataPath" : "/Users/a1111/Downloads/Telegram Desktop/fitbod-master/ios/DerivedData3",
      "indexDataStoreFolderPath" : "/Users/a1111/Downloads/Telegram Desktop/fitbod-master/ios/DerivedData3/Runner/Index.noindex/DataStore",
      "indexEnableDataStore" : true,
      "indexPCHPath" : "/Users/a1111/Downloads/Telegram Desktop/fitbod-master/ios/DerivedData3/Runner/Index.noindex/PrecompiledHeaders",
      "pchPath" : "/Users/a1111/Downloads/Telegram Desktop/fitbod-master/ios/DerivedData3/Runner/Build/Intermediates.noindex/PrecompiledHeaders"
    },
    "configurationName" : "Debug",
    "overrides" : {
      "commandLine" : {
        "table" : {
          "BUILD_DIR" : "/Users/a1111/Downloads/Telegram Desktop/fitbod-master/build/ios",
          "COMPILER_INDEX_STORE_ENABLE" : "NO",
          "FLUTTER_SUPPRESS_ANALYTICS" : "true",
          "SCRIPT_OUTPUT_STREAM_FILE" : "/var/folders/3p/2r6d4vkx3bs6gt6z00xyg41r0000gn/T/flutter_tools.8H0RoC/flutter_ios_build_temp_dirY7dkcC/pipe_to_stdout",
          "SDKROOT" : "iphonesimulator18.2"
        }
      },
      "synthesized" : {
        "table" : {
          "ACTION" : "build",
          "ASSETCATALOG_FILTER_FOR_DEVICE_MODEL" : "iPhone17,1",
          "ASSETCATALOG_FILTER_FOR_DEVICE_OS_VERSION" : "18.3.1",
          "ASSETCATALOG_FILTER_FOR_THINNING_DEVICE_CONFIGURATION" : "iPhone17,1",
          "BUILD_ACTIVE_RESOURCES_ONLY" : "YES",
          "ENABLE_PREVIEWS" : "NO",
          "ENABLE_XOJIT_PREVIEWS" : "YES",
          "TARGET_DEVICE_IDENTIFIER" : "C1B227A3-1226-49C1-BB00-824B330DF02D",
          "TARGET_DEVICE_MODEL" : "iPhone17,1",
          "TARGET_DEVICE_OS_VERSION" : "18.3.1",
          "TARGET_DEVICE_PLATFORM_NAME" : "iphonesimulator"
        }
      }
    }
  },
  "schemeCommand" : "launch",
  "showNonLoggedProgress" : true,
  "useDryRun" : false,
  "useImplicitDependencies" : true,
  "useLegacyBuildLocations" : false,
  "useParallelTargets" : true
}